{
  "checkpoint_version": "v1.0",
  "gate": "NOTION-DEEP-STRUCTURE-METADATA-GATE — Y-OS ROOT FIRST",
  "status": "NOTION_SCAN_CHECKPOINT_METADATA_ONLY_IN_PROGRESS_READY_FOR_GUARDIAN_REVIEW",
  "scan_mode": "metadata_only",
  "partial": true,
  "checkpoint_date": "2026-07-03",
  "root": {
    "id": "39135e21-8cf8-8092-8d5c-f4c2e0b680ae",
    "title": "- Y-OS ROOT -",
    "type": "page"
  },
  "metrics": {
    "nodes_visited": 53,
    "max_depth_reached": 7,
    "pages_discovered": 47,
    "databases_discovered": 6,
    "archived": 0,
    "inaccessible": 0,
    "duplicate_titles": 2,
    "l2_branches_total": 16,
    "l2_branches_scanned": 2,
    "l2_branches_pending": 14
  },
  "scanned_branches": [
    {"branch": "Y-OS ROOT", "depth": 1, "status": "complete"},
    {"branch": "Y-OS TEAM", "depth": 2, "status": "entered_children_pending"},
    {"branch": "GOVERNANCE", "depth": "2-5", "status": "complete"},
    {"branch": "ARCHITECTURE", "depth": "2-7", "status": "in_progress_active_at_checkpoint"}
  ],
  "active_branch_at_checkpoint": "ARCHITECTURE → Y-OS Multi-Agents Hub → TECH → Registre Connecteurs Manus → factsheets (d=7)",
  "databases_discovered": [
    {"title": "Y World — Node Registry", "rows": 30, "depth": 5, "parent": "Y World — Ontology Hub", "flag": null},
    {"title": "Y World — Relationship Map", "rows": 55, "depth": 5, "parent": "Y World — Ontology Hub", "flag": null},
    {"title": "Y World — Merge Map", "rows": 34, "depth": 5, "parent": "Y World — Ontology Hub", "flag": null},
    {"title": "Y World — Quarantine", "rows": 6, "depth": 5, "parent": "Y World — Ontology Hub", "flag": null},
    {"title": "Y World — Archive / Deprecated", "rows": 10, "depth": 5, "parent": "Y World — Ontology Hub", "flag": null},
    {"title": "Y World — Node Registry", "rows": 0, "depth": 5, "parent": "Y World — Ontology Hub", "flag": "DUPLICATE_TITLE_POSSIBLE_STAGING_SPLIT"}
  ],
  "flags": [
    {
      "type": "DUPLICATE_TITLE",
      "title": "Y World — Node Registry",
      "occurrences": 2,
      "rows": [30, 0],
      "note": "Possible staging/production split — requires Guardian clarification"
    },
    {
      "type": "DUPLICATE_TITLE",
      "title": "Y-OS — Dashboard Agents Schedulés",
      "occurrences": 2,
      "depth": 6,
      "note": "Duplicate title at same depth — requires Guardian clarification"
    }
  ],
  "metadata_fields_captured": [
    "id", "title", "type", "depth", "parent_id", "parent_title",
    "url", "created_time", "last_edited_time", "has_children",
    "child_count", "archived", "row_count", "schema_property_count"
  ],
  "explicitly_not_captured": [
    "page_body", "rich_text_blocks", "database_row_content",
    "semantic_extraction", "property_values_beyond_title",
    "file_attachments", "comments", "user_member_data"
  ],
  "compliance": {
    "page_bodies_read": false,
    "source_mutation": false,
    "merge_normalization_synthesis": false,
    "broad_workspace_dump": false,
    "canonicalization": false,
    "notion_mutation": false,
    "secrets_captured": false
  },
  "pending_l2_branches": [
    "MEMORY MGMT",
    "CAR — Cognitive & Agent Router",
    "and 12 others (not yet reached)"
  ],
  "recommendation": "Pause expansion. Guardian review required before continuing to remaining 14 L2 branches or expanding to other ROOT workspaces."
}
